gl_parser/__init__.py
gl_parser/cli/__init__.py
gl_parser/cli/cli_commands.py
gl_parser/cli/config_commands.py
gl_parser/cli/convert_commmands.py
gl_parser/config/__init__.py
gl_parser/config/configuration.py
gl_parser/enums.py
gl_parser/exceptions.py
gl_parser/models.py
gl_parser/parsers.py
gl_parser/settings.py
gl_parser/utils.py
gl_parser/writers.py
gl_parser-1.1.2.dist-info/entry_points.txt
gl_parser-1.1.2.dist-info/LICENSE
gl_parser-1.1.2.dist-info/WHEEL
gl_parser-1.1.2.dist-info/METADATA
gl_parser-1.1.2.dist-info/RECORD
